src/__init__.py
src/cli.py
src/commands/__init__.py
src/commands/auth.py
src/commands/run.py
src/core/__init__.py
src/core/filewalker.py
src/core/http_client.py
src/core/runner.py
src/core/websocket_base.py
src/core/websocket_client.py
src/models/__init__.py
src/models/log.py
src/models/message.py
src/output_msg/__init__.py
src/output_msg/auth_msg.py
src/settings/__init__.py
src/settings/base.py
src/settings/prod.py
src/urls/__init__.py
src/urls/auth.py
src/urls/run.py
src/utils/__init__.py
src/utils/cache.py
src/utils/config.py
src/utils/credentials.py
src/utils/log.py
src/utils/parser.py
src/utils/path.py
src/utils/print.py
src/version.py
steev-0.1.3.dist-info/METADATA
steev-0.1.3.dist-info/WHEEL
steev-0.1.3.dist-info/entry_points.txt
steev-0.1.3.dist-info/RECORD
