Metadata-Version: 2.3
Name: steev
Version: 0.1.3
Summary: steev cli
Keywords: steev,ml,ai,agent,experiment,automation
Author: SangUk Park
Author-email: psycoder@steev.io
Requires-Python: >=3.11,<4.0
Classifier: Operating System :: OS Independent
Classifier: Programming Language :: Python :: 3
Classifier: Programming Language :: Python :: 3.11
Classifier: Programming Language :: Python :: 3.12
Classifier: Programming Language :: Python :: 3.13
Requires-Dist: click (>=8.1.8,<9.0.0)
Requires-Dist: pydantic (>=2.10.5,<3.0.0)
Requires-Dist: pyjwt (>=2.10.1,<3.0.0)
Requires-Dist: python-dotenv (>=1.0.1,<2.0.0)
Requires-Dist: pyyaml (>=6.0.2,<7.0.0)
Requires-Dist: requests (>=2.32.3,<3.0.0)
Requires-Dist: websocket-client (>=1.8.0,<2.0.0)
Project-URL: Homepage, https://steev.io
Project-URL: Repository, https://github.com/TBD-Labs/steev-cli
